single_cartpole_custom_gym_env/Cartpole.py
single_cartpole_custom_gym_env/__init__.py
single_cartpole_custom_gym_env/event_handler.py
single_cartpole_custom_gym_env/single_cartpole_env.py
single_cartpole_custom_gym_env/img/icon.png
single_cartpole_custom_gym_env-1.2.5.dist-info/METADATA
single_cartpole_custom_gym_env-1.2.5.dist-info/WHEEL
single_cartpole_custom_gym_env-1.2.5.dist-info/top_level.txt
single_cartpole_custom_gym_env-1.2.5.dist-info/RECORD
