Metadata-Version: 2.1
Name: single-cartpole-custom-gym-env
Version: 1.2.5
Summary: OpenAI Gym environment designed for training RL agents to bring CartPole upright and its further balancing.
Home-page: https://github.com/marek-robak/Single-cartpole-custom-gym-env-for-reinforcement-learning.git
Download-URL: https://pypi.org/project/single-cartpole-custom-gym-env/
Author: Marek Robak
Author-email: maro.robak@gmail.com
License: UNKNOWN
Keywords: reinforcement learning,gym environment,StableBaselines3,OpenAI Gym
Platform: UNKNOWN
Requires-Dist: gym
Requires-Dist: pygame
Requires-Dist: pymunk
Requires-Dist: numpy
Requires-Dist: stable-baselines3[extra]
